MANIFEST.in
README.md
requirements.txt
setup.cfg
setup.py
registration/__init__.py
registration/model.py
registration/transforms.py
registration/utils.py
registration/algorithms/__init__.py
registration/algorithms/crosscorr.py
test/test_crosscorr.py
thunder_registration.egg-info/PKG-INFO
thunder_registration.egg-info/SOURCES.txt
thunder_registration.egg-info/dependency_links.txt
thunder_registration.egg-info/requires.txt
thunder_registration.egg-info/top_level.txt