Metadata-Version: 1.0
Name: thunder-registration
Version: 1.0.1
Summary: algorithms for image registration
Home-page: https://github.com/thunder-project/thunder-registration
Author: freeman-lab
Author-email: the.freeman.lab@gmail.com
License: MIT
Platform: UNKNOWN
